zc/buildout/__init__.py
zc/buildout/_package_index.py
zc/buildout/buildout.py
zc/buildout/configparser.py
zc/buildout/download.py
zc/buildout/easy_install.py
zc/buildout/patches.py
zc/buildout/pep425tags.py
zc/buildout/rmtree.py
zc/buildout/testing.py
zc/buildout/testing.txt
zc/buildout/testrecipes.py
zc/buildout/utils.py
zc/buildout/tests/__init__.py
zc/buildout/tests/allow-unknown-extras.txt
zc/buildout/tests/allowhosts.txt
zc/buildout/tests/buildout.txt
zc/buildout/tests/configparser.test
zc/buildout/tests/configuration.txt
zc/buildout/tests/debugging.txt
zc/buildout/tests/dependencylinks.txt
zc/buildout/tests/download.txt
zc/buildout/tests/downloadcache.txt
zc/buildout/tests/easy_install.txt
zc/buildout/tests/extending.txt
zc/buildout/tests/extends-cache.txt
zc/buildout/tests/extensions.txt
zc/buildout/tests/init.txt
zc/buildout/tests/options.txt
zc/buildout/tests/repeatable.txt
zc/buildout/tests/runsetup.txt
zc/buildout/tests/setup.txt
zc/buildout/tests/test_all.py
zc/buildout/tests/test_extras.py
zc/buildout/tests/test_increment.py
zc/buildout/tests/test_unit.py
zc/buildout/tests/testing_bugfix.txt
zc/buildout/tests/update.txt
zc/buildout/tests/windows.txt
zc/buildout/tests/recipes/README.txt
zc/buildout/tests/recipes/setup.py
zc/buildout/tests/recipes/src/debug.py
zc/buildout/tests/recipes/src/environ.py
zc/buildout/tests/recipes/src/mkdir.py
zc_buildout-5.0.0.dist-info/licenses/LICENSE.txt
zc_buildout-5.0.0.dist-info/METADATA
zc_buildout-5.0.0.dist-info/WHEEL
zc_buildout-5.0.0.dist-info/entry_points.txt
zc_buildout-5.0.0.dist-info/top_level.txt
zc_buildout-5.0.0.dist-info/RECORD
