Metadata-Version: 2.4
Name: zc.buildout
Version: 5.0.0
Summary: System for managing development buildouts
Home-page: http://buildout.org
Author: Jim Fulton
Author-email: jim@zope.com
License: ZPL 2.1
Keywords: development build
Classifier: Development Status :: 6 - Mature
Classifier: Intended Audience :: Developers
Classifier: License :: OSI Approved :: Zope Public License
Classifier: Programming Language :: Python
Classifier: Programming Language :: Python :: 3.9
Classifier: Programming Language :: Python :: 3.10
Classifier: Programming Language :: Python :: 3.11
Classifier: Programming Language :: Python :: 3.12
Classifier: Programming Language :: Python :: 3.13
Classifier: Topic :: Software Development :: Build Tools
Classifier: Topic :: Software Development :: Libraries :: Python Modules
Requires-Python: >=3.9
License-File: LICENSE.txt
Requires-Dist: setuptools>=61.0.0
Requires-Dist: packaging>=23.2
Requires-Dist: pip
Requires-Dist: wheel
Provides-Extra: test
Requires-Dist: zope.testing; extra == "test"
Requires-Dist: manuel; extra == "test"
Requires-Dist: bobo==2.3.0; extra == "test"
Requires-Dist: zdaemon; extra == "test"
Requires-Dist: zc.zdaemonrecipe; extra == "test"
Requires-Dist: zc.recipe.deployment; extra == "test"
Dynamic: author
Dynamic: author-email
Dynamic: classifier
Dynamic: description
Dynamic: home-page
Dynamic: keywords
Dynamic: license
Dynamic: license-file
Dynamic: provides-extra
Dynamic: requires-dist
Dynamic: requires-python
Dynamic: summary
